PyVirtry/__init__.py
PyVirtry/VirtualTryOn/__init__.py
PyVirtry/VirtualTryOn/apply_net.py
PyVirtry/VirtualTryOn/models.py
PyVirtry/VirtualTryOn/test.py
PyVirtry/VirtualTryOn/utils_mask.py
PyVirtry/VirtualTryOn/densepose/__init__.py
PyVirtry/VirtualTryOn/densepose/config.py
PyVirtry/VirtualTryOn/densepose/converters/__init__.py
PyVirtry/VirtualTryOn/densepose/converters/base.py
PyVirtry/VirtualTryOn/densepose/converters/builtin.py
PyVirtry/VirtualTryOn/densepose/converters/chart_output_hflip.py
PyVirtry/VirtualTryOn/densepose/converters/chart_output_to_chart_result.py
PyVirtry/VirtualTryOn/densepose/converters/hflip.py
PyVirtry/VirtualTryOn/densepose/converters/segm_to_mask.py
PyVirtry/VirtualTryOn/densepose/converters/to_chart_result.py
PyVirtry/VirtualTryOn/densepose/converters/to_mask.py
PyVirtry/VirtualTryOn/densepose/data/__init__.py
PyVirtry/VirtualTryOn/densepose/data/build.py
PyVirtry/VirtualTryOn/densepose/data/combined_loader.py
PyVirtry/VirtualTryOn/densepose/data/dataset_mapper.py
PyVirtry/VirtualTryOn/densepose/data/image_list_dataset.py
PyVirtry/VirtualTryOn/densepose/data/inference_based_loader.py
PyVirtry/VirtualTryOn/densepose/data/utils.py
PyVirtry/VirtualTryOn/densepose/data/datasets/__init__.py
PyVirtry/VirtualTryOn/densepose/data/datasets/builtin.py
PyVirtry/VirtualTryOn/densepose/data/datasets/chimpnsee.py
PyVirtry/VirtualTryOn/densepose/data/datasets/coco.py
PyVirtry/VirtualTryOn/densepose/data/datasets/dataset_type.py
PyVirtry/VirtualTryOn/densepose/data/datasets/lvis.py
PyVirtry/VirtualTryOn/densepose/data/meshes/__init__.py
PyVirtry/VirtualTryOn/densepose/data/meshes/builtin.py
PyVirtry/VirtualTryOn/densepose/data/meshes/catalog.py
PyVirtry/VirtualTryOn/densepose/data/samplers/__init__.py
PyVirtry/VirtualTryOn/densepose/data/samplers/densepose_base.py
PyVirtry/VirtualTryOn/densepose/data/samplers/densepose_confidence_based.py
PyVirtry/VirtualTryOn/densepose/data/samplers/densepose_cse_base.py
PyVirtry-1.0.2.dist-info/METADATA
PyVirtry-1.0.2.dist-info/WHEEL
PyVirtry-1.0.2.dist-info/top_level.txt
PyVirtry-1.0.2.dist-info/RECORD
